ipmike/__init__.py
ipmike/ipmike.py
ipmike-0.1.4.dist-info/LICENSE.md
ipmike-0.1.4.dist-info/METADATA
ipmike-0.1.4.dist-info/WHEEL
ipmike-0.1.4.dist-info/top_level.txt
ipmike-0.1.4.dist-info/RECORD
